DESCRIPTION.rst
MANIFEST.in
README.rst
acemorse.py
example.py
setup.cfg
setup.py
AceMorse.egg-info/PKG-INFO
AceMorse.egg-info/SOURCES.txt
AceMorse.egg-info/dependency_links.txt
AceMorse.egg-info/top_level.txt